Workbook

Sheet A̳ssets
B3: Paleta de Cores
B5: # 9BC848 | C5: Xbox Color | E5: # E8E6E9 | F5: negative zone
B6: # 22C55E | C6: Xbox Color
B7: # 2AE6B1 | C7: Menus
B8: # 5BF6A8 | C8: Menus
B12: Logos | J12: ícones

Sheet B̳ases
A1: Subscriber ID | B1: Name | C1: Plan | D1: Start Date | E1: Auto Renewal | F1: Subscription Price | G1: Subscription Type | H1: EA Play Season Pass | I1: EA Play Season Pass Price | J1: Minecraft Season Pass | K1: Minecraft Season Pass Price | L1: Coupon Value | M1: Total Value
A2: 3231 | B2: João Silva | C2: Ultimate | D2: 45292 | E2: Yes | F2: 15 | G2: Monthly | H2: Yes | I2: 30 | J2: Yes | K2: 20 | L2: 5 | M2: 60
A3: 3232 | B3: Maria Oliveira | C3: Core | D3: 45306 | E3: No | F3: 5 | G3: Annual | H3: No | I3: - | J3: No | K3: 0 | L3: 0 | M3: 5
A4: 3233 | B4: Lucas Fernandes | C4: Standard | D4: 45332 | E4: Yes | F4: 10 | G4: Quarterly | H4: No | I4: - | J4: Yes | K4: 20 | L4: 10 | M4: 20
A5: 3234 | B5: Ana Souza | C5: Ultimate | D5: 45342 | E5: No | F5: 15 | G5: Monthly | H5: Yes | I5: 30 | J5: Yes | K5: 20 | L5: 3 | M5: 62
A6: 3235 | B6: Pedro Gonçalves | C6: Core | D6: 45356 | E6: Yes | F6: 5 | G6: Monthly | H6: No | I6: - | J6: No | K6: 0 | L6: 1 | M6: 4
A7: 3236 | B7: Felipe Costa | C7: Standard | D7: 45353 | E7: No | F7: 10 | G7: Monthly | H7: No | I7: - | J7: Yes | K7: 20 | L7: 2 | M7: 28
A8: 3237 | B8: Camila Ribeiro | C8: Ultimate | D8: 45354 | E8: Yes | F8: 15 | G8: Quarterly | H8: Yes | I8: 30 | J8: Yes | K8: 20 | L8: 10 | M8: 55
A9: 3238 | B9: André Mendes | C9: Core | D9: 45355 | E9: Yes | F9: 5 | G9: Annual | H9: No | I9: - | J9: No | K9: 0 | L9: 0 | M9: 5
A10: 3239 | B10: Sofia Almeida | C10: Ultimate | D10: 45356 | E10: No | F10: 15 | G10: Monthly | H10: Yes | I10: 30 | J10: Yes | K10: 20 | L10: 5 | M10: 60
A11: 3240 | B11: Bruno Martins | C11: Standard | D11: 45357 | E11: Yes | F11: 10 | G11: Quarterly | H11: No | I11: - | J11: Yes | K11: 20 | L11: 15 | M11: 15
A12: 3241 | B12: Rita Castro | C12: Core | D12: 45358 | E12: No | F12: 5 | G12: Monthly | H12: No | I12: - | J12: No | K12: 0 | L12: 1 | M12: 4
A13: 3242 | B13: Marco Túlio | C13: Ultimate | D13: 45359 | E13: Yes | F13: 15 | G13: Annual | H13: Yes | I13: 30 | J13: Yes | K13: 20 | L13: 20 | M13: 45
A14: 3243 | B14: Lívia Silveira | C14: Standard | D14: 45360 | E14: No | F14: 10 | G14: Monthly | H14: No | I14: - | J14: Yes | K14: 20 | L14: 10 | M14: 20
A15: 3244 | B15: Diogo Sousa | C15: Core | D15: 45361 | E15: Yes | F15: 5 | G15: Quarterly | H15: No | I15: - | J15: No | K15: 0 | L15: 0 | M15: 5
A16: 3245 | B16: Fernanda Lima | C16: Ultimate | D16: 45362 | E16: No | F16: 15 | G16: Monthly | H16: Yes | I16: 30 | J16: Yes | K16: 20 | L16: 8 | M16: 57
A17: 3246 | B17: Caio Pereira | C17: Standard | D17: 45363 | E17: Yes | F17: 10 | G17: Annual | H17: No | I17: - | J17: Yes | K17: 20 | L17: 12 | M17: 18
A18: 3247 | B18: Beatriz Gomes | C18: Core | D18: 45364 | E18: No | F18: 5 | G18: Monthly | H18: No | I18: - | J18: No | K18: 0 | L18: 2 | M18: 3
A19: 3248 | B19: Cesar Oliveira | C19: Ultimate | D19: 45365 | E19: Yes | F19: 15 | G19: Quarterly | H19: Yes | I19: 30 | J19: Yes | K19: 20 | L19: 7 | M19: 58
A20: 3249 | B20: Débora Machado | C20: Standard | D20: 45366 | E20: No | F20: 10 | G20: Monthly | H20: No | I20: - | J20: Yes | K20: 20 | L20: 5 | M20: 25
A21: 3250 | B21: Eduardo Vargas | C21: Core | D21: 45367 | E21: Yes | F21: 5 | G21: Annual | H21: No | I21: - | J21: No | K21: 0 | L21: 0 | M21: 5
A22: 3251 | B22: Gabriela Santos | C22: Ultimate | D22: 45368 | E22: No | F22: 15 | G22: Monthly | H22: Yes | I22: 30 | J22: Yes | K22: 20 | L22: 3 | M22: 62
A23: 3252 | B23: Henrique Dias | C23: Standard | D23: 45369 | E23: Yes | F23: 10 | G23: Quarterly | H23: No | I23: - | J23: Yes | K23: 20 | L23: 15 | M23: 15
A24: 3253 | B24: Isabela Moreira | C24: Core | D24: 45370 | E24: No | F24: 5 | G24: Monthly | H24: No | I24: - | J24: No | K24: 0 | L24: 1 | M24: 4
A25: 3254 | B25: Joaquim Barbosa | C25: Ultimate | D25: 45371 | E25: Yes | F25: 15 | G25: Annual | H25: Yes | I25: 30 | J25: Yes | K25: 20 | L25: 20 | M25: 45
A26: 3255 | B26: Lara Rocha | C26: Standard | D26: 45372 | E26: No | F26: 10 | G26: Monthly | H26: No | I26: - | J26: Yes | K26: 20 | L26: 10 | M26: 20
A27: 3256 | B27: Matheus Silva | C27: Core | D27: 45373 | E27: Yes | F27: 5 | G27: Quarterly | H27: No | I27: - | J27: No | K27: 0 | L27: 0 | M27: 5
A28: 3257 | B28: Nicole Costa | C28: Ultimate | D28: 45374 | E28: No | F28: 15 | G28: Monthly | H28: Yes | I28: 30 | J28: Yes | K28: 20 | L28: 5 | M28: 60
A29: 3258 | B29: Otávio Mendonça | C29: Standard | D29: 45375 | E29: Yes | F29: 10 | G29: Annual | H29: No | I29: - | J29: Yes | K29: 20 | L29: 15 | M29: 15
A30: 3259 | B30: Paula Ferreira | C30: Core | D30: 45376 | E30: No | F30: 5 | G30: Monthly | H30: No | I30: - | J30: No | K30: 0 | L30: 1 | M30: 4
A31: 3260 | B31: Raquel Alves | C31: Ultimate | D31: 45377 | E31: Yes | F31: 15 | G31: Quarterly | H31: Yes | I31: 30 | J31: Yes | K31: 20 | L31: 7 | M31: 58
A32: 3261 | B32: Samuel Pires | C32: Standard | D32: 45378 | E32: No | F32: 10 | G32: Monthly | H32: No | I32: - | J32: Yes | K32: 20 | L32: 10 | M32: 20
A33: 3262 | B33: Tânia Barros | C33: Core | D33: 45379 | E33: Yes | F33: 5 | G33: Annual | H33: No | I33: - | J33: No | K33: 0 | L33: 0 | M33: 5
A34: 3263 | B34: Vinicius Lima | C34: Ultimate | D34: 45380 | E34: No | F34: 15 | G34: Monthly | H34: Yes | I34: 30 | J34: Yes | K34: 20 | L34: 3 | M34: 62
A35: 3264 | B35: Yasmin Teixeira | C35: Standard | D35: 45381 | E35: Yes | F35: 10 | G35: Quarterly | H35: No | I35: - | J35: Yes | K35: 20 | L35: 15 | M35: 15
A36: 3265 | B36: Zé Carlos | C36: Core | D36: 45382 | E36: No | F36: 5 | G36: Monthly | H36: No | I36: - | J36: No | K36: 0 | L36: 1 | M36: 4
A37: 3266 | B37: Amanda Nogueira | C37: Core | D37: 45383 | E37: Yes | F37: 5 | G37: Monthly | H37: No | I37: - | J37: No | K37: 0 | L37: 0 | M37: 5
A38: 3267 | B38: Bruno Cavalheiro | C38: Ultimate | D38: 45384 | E38: No | F38: 15 | G38: Quarterly | H38: Yes | I38: 30 | J38: Yes | K38: 20 | L38: 7 | M38: 58
A39: 3268 | B39: Carla Dias | C39: Standard | D39: 45385 | E39: Yes | F39: 10 | G39: Annual | H39: No | I39: - | J39: Yes | K39: 20 | L39: 10 | M39: 20
A40: 3269 | B40: Diego Fontes | C40: Core | D40: 45386 | E40: No | F40: 5 | G40: Quarterly | H40: No | I40: - | J40: No | K40: 0 | L40: 1 | M40: 4
A41: 3270 | B41: Eunice Lima | C41: Ultimate | D41: 45387 | E41: Yes | F41: 15 | G41: Monthly | H41: Yes | I41: 30 | J41: Yes | K41: 20 | L41: 15 | M41: 50
A42: 3271 | B42: Fábio Martins | C42: Standard | D42: 45388 | E42: No | F42: 10 | G42: Monthly | H42: No | I42: - | J42: Yes | K42: 20 | L42: 5 | M42: 25
A43: 3272 | B43: Gisele Araújo | C43: Core | D43: 45389 | E43: Yes | F43: 5 | G43: Annual | H43: No | I43: - | J43: No | K43: 0 | L43: 0 | M43: 5
A44: 3273 | B44: Hélio Castro | C44: Ultimate | D44: 45390 | E44: No | F44: 15 | G44: Quarterly | H44: Yes | I44: 30 | J44: Yes | K44: 20 | L44: 20 | M44: 45
A45: 3274 | B45: Ingrid Menezes | C45: Standard | D45: 45391 | E45: Yes | F45: 10 | G45: Quarterly | H45: No | I45: - | J45: Yes | K45: 20 | L45: 12 | M45: 18
A46: 3275 | B46: Jorge Baptista | C46: Core | D46: 45392 | E46: No | F46: 5 | G46: Monthly | H46: No | I46: - | J46: No | K46: 0 | L46: 2 | M46: 3
A47: 3276 | B47: Kléber Oliveira | C47: Ultimate | D47: 45393 | E47: Yes | F47: 15 | G47: Annual | H47: Yes | I47: 30 | J47: Yes | K47: 20 | L47: 5 | M47: 60
A48: 3277 | B48: Luciana Freitas | C48: Standard | D48: 45394 | E48: No | F48: 10 | G48: Monthly | H48: No | I48: - | J48: Yes | K48: 20 | L48: 10 | M48: 20
A49: 3278 | B49: Márcia Eller | C49: Core | D49: 45395 | E49: Yes | F49: 5 | G49: Quarterly | H49: No | I49: - | J49: No | K49: 0 | L49: 0 | M49: 5
A50: 3279 | B50: Nilo Peçanha | C50: Ultimate | D50: 45396 | E50: No | F50: 15 | G50: Monthly | H50: Yes | I50: 30 | J50: Yes | K50: 20 | L50: 3 | M50: 62
A51: 3280 | B51: Oscar Neves | C51: Standard | D51: 45397 | E51: Yes | F51: 10 | G51: Annual | H51: No | I51: - | J51: Yes | K51: 20 | L51: 15 | M51: 15
A52: 3281 | B52: Patrícia Soares | C52: Core | D52: 45398 | E52: No | F52: 5 | G52: Monthly | H52: No | I52: - | J52: No | K52: 0 | L52: 1 | M52: 4
A53: 3282 | B53: Quirino Gonçalves | C53: Ultimate | D53: 45399 | E53: Yes | F53: 15 | G53: Quarterly | H53: Yes | I53: 30 | J53: Yes | K53: 20 | L53: 7 | M53: 58
A54: 3283 | B54: Raul Machado | C54: Standard | D54: 45400 | E54: No | F54: 10 | G54: Monthly | H54: No | I54: - | J54: Yes | K54: 20 | L54: 10 | M54: 20
A55: 3284 | B55: Sônia Lobo | C55: Core | D55: 45401 | E55: Yes | F55: 5 | G55: Annual | H55: No | I55: - | J55: No | K55: 0 | L55: 0 | M55: 5
A56: 3285 | B56: Tiago Ramos | C56: Ultimate | D56: 45402 | E56: No | F56: 15 | G56: Monthly | H56: Yes | I56: 30 | J56: Yes | K56: 20 | L56: 20 | M56: 45
A57: 3286 | B57: Ugo Pires | C57: Standard | D57: 45403 | E57: Yes | F57: 10 | G57: Quarterly | H57: No | I57: - | J57: Yes | K57: 20 | L57: 15 | M57: 15
A58: 3287 | B58: Valéria Nobre | C58: Core | D58: 45404 | E58: No | F58: 5 | G58: Monthly | H58: No | I58: - | J58: No | K58: 0 | L58: 1 | M58: 4
A59: 3288 | B59: William Siqueira | C59: Ultimate | D59: 45405 | E59: Yes | F59: 15 | G59: Annual | H59: Yes | I59: 30 | J59: Yes | K59: 20 | L59: 3 | M59: 62
A60: 3289 | B60: Xuxa Meneghel | C60: Standard | D60: 45406 | E60: No | F60: 10 | G60: Monthly | H60: No | I60: - | J60: Yes | K60: 20 | L60: 10 | M60: 20
A61: 3290 | B61: Yara Figueiredo | C61: Core | D61: 45407 | E61: Yes | F61: 5 | G61: Quarterly | H61: No | I61: - | J61: No | K61: 0 | L61: 0 | M61: 5
A62: 3291 | B62: Zacarias Alves | C62: Ultimate | D62: 45408 | E62: No | F62: 15 | G62: Monthly | H62: Yes | I62: 30 | J62: Yes | K62: 20 | L62: 5 | M62: 60
A63: 3292 | B63: Amanda Bynes | C63: Standard | D63: 45409 | E63: Yes | F63: 10 | G63: Annual | H63: No | I63: - | J63: Yes | K63: 20 | L63: 15 | M63: 15
A64: 3293 | B64: Bruno Mars | C64: Core | D64: 45410 | E64: No | F64: 5 | G64: Monthly | H64: No | I64: - | J64: No | K64: 0 | L64: 1 | M64: 4
A65: 3294 | B65: Carla Bruni | C65: Ultimate | D65: 45411 | E65: Yes | F65: 15 | G65: Quarterly | H65: Yes | I65: 30 | J65: Yes | K65: 20 | L65: 20 | M65: 45
A66: 3295 | B66: Diego Maradona | C66: Standard | D66: 45412 | E66: No | F66: 10 | G66: Monthly | H66: No | I66: - | J66: Yes | K66: 20 | L66: 5 | M66: 25
A67: 3296 | B67: Estela Marques | C67: Core | D67: 45413 | E67: No | F67: 5 | G67: Monthly | H67: No | I67: - | J67: No | K67: 0 | L67: 0 | M67: 5
A68: 3297 | B68: Fábio Nobre | C68: Ultimate | D68: 45414 | E68: Yes | F68: 15 | G68: Quarterly | H68: Yes | I68: 30 | J68: Yes | K68: 20 | L68: 7 | M68: 58
A69: 3298 | B69: Gabriel Oliveira | C69: Standard | D69: 45415 | E69: No | F69: 10 | G69: Annual | H69: No | I69: - | J69: Yes | K69: 20 | L69: 10 | M69: 20
A70: 3299 | B70: Helena Santos | C70: Core | D70: 45416 | E70: Yes | F70: 5 | G70: Quarterly | H70: No | I70: - | J70: No | K70: 0 | L70: 1 | M70: 4
A71: 3300 | B71: Ivan Carvalho | C71: Ultimate | D71: 45417 | E71: No | F71: 15 | G71: Monthly | H71: Yes | I71: 30 | J71: Yes | K71: 20 | L71: 15 | M71: 50
A72: 3301 | B72: Júlia Ferreira | C72: Standard | D72: 45418 | E72: Yes | F72: 10 | G72: Monthly | H72: No | I72: - | J72: Yes | K72: 20 | L72: 5 | M72: 25
A73: 3302 | B73: Karla Alves | C73: Core | D73: 45419 | E73: No | F73: 5 | G73: Annual | H73: No | I73: - | J73: No | K73: 0 | L73: 0 | M73: 5
A74: 3303 | B74: Lucas Mendes | C74: Ultimate | D74: 45420 | E74: Yes | F74: 15 | G74: Quarterly | H74: Yes | I74: 30 | J74: Yes | K74: 20 | L74: 20 | M74: 45
A75: 3304 | B75: Mônica Gomes | C75: Standard | D75: 45421 | E75: No | F75: 10 | G75: Quarterly | H75: No | I75: - | J75: Yes | K75: 20 | L75: 12 | M75: 18
A76: 3305 | B76: Norberto Queiroz | C76: Core | D76: 45422 | E76: Yes | F76: 5 | G76: Monthly | H76: No | I76: - | J76: No | K76: 0 | L76: 2 | M76: 3
A77: 3306 | B77: Otávio Barros | C77: Ultimate | D77: 45423 | E77: No | F77: 15 | G77: Annual | H77: Yes | I77: 30 | J77: Yes | K77: 20 | L77: 5 | M77: 60
A78: 3307 | B78: Paula Vieira | C78: Standard | D78: 45424 | E78: Yes | F78: 10 | G78: Monthly | H78: No | I78: - | J78: Yes | K78: 20 | L78: 10 | M78: 20
A79: 3308 | B79: Quentin Ramos | C79: Core | D79: 45425 | E79: No | F79: 5 | G79: Quarterly | H79: No | I79: - | J79: No | K79: 0 | L79: 0 | M79: 5
A80: 3309 | B80: Raquel Novaes | C80: Ultimate | D80: 45426 | E80: Yes | F80: 15 | G80: Monthly | H80: Yes | I80: 30 | J80: Yes | K80: 20 | L80: 3 | M80: 62
A81: 3310 | B81: Samantha Lopes | C81: Standard | D81: 45427 | E81: No | F81: 10 | G81: Annual | H81: No | I81: - | J81: Yes | K81: 20 | L81: 15 | M81: 15
A82: 3311 | B82: Tiago Martins | C82: Core | D82: 45428 | E82: Yes | F82: 5 | G82: Monthly | H82: No | I82: - | J82: No | K82: 0 | L82: 1 | M82: 4
A83: 3312 | B83: Ulysses Guimarães | C83: Ultimate | D83: 45429 | E83: No | F83: 15 | G83: Quarterly | H83: Yes | I83: 30 | J83: Yes | K83: 20 | L83: 7 | M83: 58
A84: 3313 | B84: Vanessa Silva | C84: Standard | D84: 45430 | E84: Yes | F84: 10 | G84: Monthly | H84: No | I84: - | J84: Yes | K84: 20 | L84: 10 | M84: 20
A85: 3314 | B85: William Carneiro | C85: Core | D85: 45431 | E85: No | F85: 5 | G85: Annual | H85: No | I85: - | J85: No | K85: 0 | L85: 0 | M85: 5
A86: 3315 | B86: Ximena Rocha | C86: Ultimate | D86: 45432 | E86: Yes | F86: 15 | G86: Monthly | H86: Yes | I86: 30 | J86: Yes | K86: 20 | L86: 20 | M86: 45
A87: 3316 | B87: Yasmin Figueiredo | C87: Standard | D87: 45433 | E87: No | F87: 10 | G87: Quarterly | H87: No | I87: - | J87: Yes | K87: 20 | L87: 15 | M87: 15
A88: 3317 | B88: Zara Cunha | C88: Core | D88: 45434 | E88: Yes | F88: 5 | G88: Monthly | H88: No | I88: - | J88: No | K88: 0 | L88: 1 | M88: 4
A89: 3318 | B89: Alan Teixeira | C89: Ultimate | D89: 45435 | E89: No | F89: 15 | G89: Annual | H89: Yes | I89: 30 | J89: Yes | K89: 20 | L89: 3 | M89: 62
A90: 3319 | B90: Bárbara Oliveira | C90: Standard | D90: 45436 | E90: Yes | F90: 10 | G90: Monthly | H90: No | I90: - | J90: Yes | K90: 20 | L90: 10 | M90: 20
A91: 3320 | B91: Carlos Junqueira | C91: Core | D91: 45437 | E91: No | F91: 5 | G91: Quarterly | H91: No | I91: - | J91: No | K91: 0 | L91: 0 | M91: 5
A92: 3321 | B92: Daniela Moura | C92: Ultimate | D92: 45438 | E92: Yes | F92: 15 | G92: Monthly | H92: Yes | I92: 30 | J92: Yes | K92: 20 | L92: 5 | M92: 60
A93: 3322 | B93: Eduardo Lima | C93: Standard | D93: 45439 | E93: No | F93: 10 | G93: Annual | H93: No | I93: - | J93: Yes | K93: 20 | L93: 15 | M93: 15
A94: 3323 | B94: Fabiana Araújo | C94: Core | D94: 45440 | E94: Yes | F94: 5 | G94: Monthly | H94: No | I94: - | J94: No | K94: 0 | L94: 1 | M94: 4
A95: 3324 | B95: Geraldo Ribeiro | C95: Ultimate | D95: 45441 | E95: No | F95: 15 | G95: Quarterly | H95: Yes | I95: 30 | J95: Yes | K95: 20 | L95: 20 | M95: 45
A96: 3325 | B96: Héctor Vargas | C96: Standard | D96: 45442 | E96: Yes | F96: 10 | G96: Quarterly | H96: No | I96: - | J96: Yes | K96: 20 | L96: 15 | M96: 15
A97: 3326 | B97: Isabela Fonseca | C97: Core | D97: 45443 | E97: No | F97: 5 | G97: Annual | H97: No | I97: - | J97: No | K97: 0 | L97: 0 | M97: 5
A98: 3327 | B98: João Pedro Almeida | C98: Ultimate | D98: 45444 | E98: Yes | F98: 15 | G98: Monthly | H98: Yes | I98: 30 | J98: Yes | K98: 20 | L98: 7 | M98: 58
A99: 3328 | B99: Klara Costa | C99: Standard | D99: 45445 | E99: No | F99: 10 | G99: Annual | H99: No | I99: - | J99: Yes | K99: 20 | L99: 10 | M99: 20
A100: 3329 | B100: Luciana Mendes | C100: Core | D100: 45446 | E100: Yes | F100: 5 | G100: Quarterly | H100: No | I100: - | J100: No | K100: 0 | L100: 1 | M100: 4
...

Sheet C̳álculos
A1: Cálculos do Dashboard
A2: Todas as tabelas leem a aba Bases e respondem aos filtros da aba Dashboard. Texto azul = entrada manual.
A3: Filtro | B3: Seleção (Dashboard) | C3: Critério (valor na base) | E3: Rótulo no filtro | F3: Valor na base
A4: Plano | B4: ='D̳ashboard'!B7 -> Todos | C4: =IF(B4="Todos","*",B4) -> * | E4: Mensal | F4: Monthly
A5: Tipo de assinatura | B5: ='D̳ashboard'!E7 -> Todos | C5: {=IF(B5="Todos","*",IFERROR(INDEX($F$4:$F$6,MATCH(B5,$E$4:$E$6,0)),B5))} -> * | E5: Trimestral | F5: Quarterly
A6: Renovação automática | B6: ='D̳ashboard'!H7 -> Todos | C6: {=IF(B6="Todos","*",IFERROR(INDEX($F$7:$F$8,MATCH(B6,$E$7:$E$8,0)),B6))} -> * | E6: Anual | F6: Annual
E7: Sim | F7: Yes
A8: Ano de referência (meses do gráfico) | B8: 2024 | C8: Entrada manual: a base cobre jan–dez/2024. | E8: Não | F8: No
A10: T1 · Receita, cupons e ticket por plano (ignora o filtro de Plano)
A11: Plano | B11: Receita | C11: Assinantes | D11: Cupons | E11: Desconto s/ valor bruto | F11: Ticket médio | J11: Auxiliar do Top 10 (uma linha por assinatura da base)
A12: Core | B12: =SUMIFS('B̳ases'!$M$2:$M$296,'B̳ases'!$C$2:$C$296,$A12,'B̳ases'!$G$2:$G$296,$C$5,'B̳ases'!$E$2:$E$296,$C$6) -> R$ 444 | C12: =COUNTIFS('B̳ases'!$C$2:$C$296,$A12,'B̳ases'!$G$2:$G$296,$C$5,'B̳ases'!$E$2:$E$296,$C$6) -> 101 | D12: =SUMIFS('B̳ases'!$L$2:$L$296,'B̳ases'!$C$2:$C$296,$A12,'B̳ases'!$G$2:$G$296,$C$5,'B̳ases'!$E$2:$E$296,$C$6) -> R$ 61 | E12: =IFERROR(D12/(B12+D12),0) -> 12.1% | F12: =IFERROR(B12/C12,0) -> R$ 4.40 | J12: Chave (valor + desempate)
A13: Standard | B13: =SUMIFS('B̳ases'!$M$2:$M$296,'B̳ases'!$C$2:$C$296,$A13,'B̳ases'!$G$2:$G$296,$C$5,'B̳ases'!$E$2:$E$296,$C$6) -> R$ 1,801 | C13: =COUNTIFS('B̳ases'!$C$2:$C$296,$A13,'B̳ases'!$G$2:$G$296,$C$5,'B̳ases'!$E$2:$E$296,$C$6) -> 96 | D13: =SUMIFS('B̳ases'!$L$2:$L$296,'B̳ases'!$C$2:$C$296,$A13,'B̳ases'!$G$2:$G$296,$C$5,'B̳ases'!$E$2:$E$296,$C$6) -> R$ 1,079 | E13: =IFERROR(D13/(B13+D13),0) -> 37.5% | F13: =IFERROR(B13/C13,0) -> R$ 18.76 | J13: =IF(AND(OR($B$4="Todos",'B̳ases'!$C2=$B$4),OR($B$5="Todos",'B̳ases'!$G2=$C$5),OR($B$6="Todos",'B̳ases'!$E2=$C$6)),'B̳ases'!$M2+ROW()/1000000,"") -> 60.000013
A14: Ultimate | B14: =SUMIFS('B̳ases'!$M$2:$M$296,'B̳ases'!$C$2:$C$296,$A14,'B̳ases'!$G$2:$G$296,$C$5,'B̳ases'!$E$2:$E$296,$C$6) -> R$ 5,388 | C14: =COUNTIFS('B̳ases'!$C$2:$C$296,$A14,'B̳ases'!$G$2:$G$296,$C$5,'B̳ases'!$E$2:$E$296,$C$6) -> 98 | D14: =SUMIFS('B̳ases'!$L$2:$L$296,'B̳ases'!$C$2:$C$296,$A14,'B̳ases'!$G$2:$G$296,$C$5,'B̳ases'!$E$2:$E$296,$C$6) -> R$ 982 | E14: =IFERROR(D14/(B14+D14),0) -> 15.4% | F14: =IFERROR(B14/C14,0) -> R$ 54.98 | J14: =IF(AND(OR($B$4="Todos",'B̳ases'!$C3=$B$4),OR($B$5="Todos",'B̳ases'!$G3=$C$5),OR($B$6="Todos",'B̳ases'!$E3=$C$6)),'B̳ases'!$M3+ROW()/1000000,"") -> 5.000014
A15: Total | B15: =SUM(B12:B14) -> R$ 7,633 | C15: =SUM(C12:C14) -> 295 | D15: =SUM(D12:D14) -> R$ 2,122 | E15: =IFERROR(D15/(B15+D15),0) -> 21.8% | F15: =IFERROR(B15/C15,0) -> R$ 25.87 | J15: =IF(AND(OR($B$4="Todos",'B̳ases'!$C4=$B$4),OR($B$5="Todos",'B̳ases'!$G4=$C$5),OR($B$6="Todos",'B̳ases'!$E4=$C$6)),'B̳ases'!$M4+ROW()/1000000,"") -> 20.000015
J16: =IF(AND(OR($B$4="Todos",'B̳ases'!$C5=$B$4),OR($B$5="Todos",'B̳ases'!$G5=$C$5),OR($B$6="Todos",'B̳ases'!$E5=$C$6)),'B̳ases'!$M5+ROW()/1000000,"") -> 62.000016
A17: T2 · Evolução mensal (aplica todos os filtros) | J17: =IF(AND(OR($B$4="Todos",'B̳ases'!$C6=$B$4),OR($B$5="Todos",'B̳ases'!$G6=$C$5),OR($B$6="Todos",'B̳ases'!$E6=$C$6)),'B̳ases'!$M6+ROW()/1000000,"") -> 4.000017
A18: Mês | B18: Início do mês | C18: Receita | D18: Novos assinantes | J18: =IF(AND(OR($B$4="Todos",'B̳ases'!$C7=$B$4),OR($B$5="Todos",'B̳ases'!$G7=$C$5),OR($B$6="Todos",'B̳ases'!$E7=$C$6)),'B̳ases'!$M7+ROW()/1000000,"") -> 28.000018
A19: Jan | B19: =DATE($B$8,1,1) -> 01/2024 | C19: =SUMIFS('B̳ases'!$M$2:$M$296,'B̳ases'!$D$2:$D$296,">="&B19,'B̳ases'!$D$2:$D$296,"<"&DATE(YEAR(B19),MONTH(B19)+1,1),'B̳ases'!$C$2:$C$296,$C$4,'B̳ases'!$G$2:$G$296,$C$5,'B̳ases'!$E$2:$E$296,$C$6) -> R$ 65 | D19: =COUNTIFS('B̳ases'!$D$2:$D$296,">="&B19,'B̳ases'!$D$2:$D$296,"<"&DATE(YEAR(B19),MONTH(B19)+1,1),'B̳ases'!$C$2:$C$296,$C$4,'B̳ases'!$G$2:$G$296,$C$5,'B̳ases'!$E$2:$E$296,$C$6) -> 2 | J19: =IF(AND(OR($B$4="Todos",'B̳ases'!$C8=$B$4),OR($B$5="Todos",'B̳ases'!$G8=$C$5),OR($B$6="Todos",'B̳ases'!$E8=$C$6)),'B̳ases'!$M8+ROW()/1000000,"") -> 55.000019
A20: Fev | B20: =DATE($B$8,2,1) -> 02/2024 | C20: =SUMIFS('B̳ases'!$M$2:$M$296,'B̳ases'!$D$2:$D$296,">="&B20,'B̳ases'!$D$2:$D$296,"<"&DATE(YEAR(B20),MONTH(B20)+1,1),'B̳ases'!$C$2:$C$296,$C$4,'B̳ases'!$G$2:$G$296,$C$5,'B̳ases'!$E$2:$E$296,$C$6) -> R$ 82 | D20: =COUNTIFS('B̳ases'!$D$2:$D$296,">="&B20,'B̳ases'!$D$2:$D$296,"<"&DATE(YEAR(B20),MONTH(B20)+1,1),'B̳ases'!$C$2:$C$296,$C$4,'B̳ases'!$G$2:$G$296,$C$5,'B̳ases'!$E$2:$E$296,$C$6) -> 2 | J20: =IF(AND(OR($B$4="Todos",'B̳ases'!$C9=$B$4),OR($B$5="Todos",'B̳ases'!$G9=$C$5),OR($B$6="Todos",'B̳ases'!$E9=$C$6)),'B̳ases'!$M9+ROW()/1000000,"") -> 5.000020
A21: Mar | B21: =DATE($B$8,3,1) -> 03/2024 | C21: =SUMIFS('B̳ases'!$M$2:$M$296,'B̳ases'!$D$2:$D$296,">="&B21,'B̳ases'!$D$2:$D$296,"<"&DATE(YEAR(B21),MONTH(B21)+1,1),'B̳ases'!$C$2:$C$296,$C$4,'B̳ases'!$G$2:$G$296,$C$5,'B̳ases'!$E$2:$E$296,$C$6) -> R$ 801 | D21: =COUNTIFS('B̳ases'!$D$2:$D$296,">="&B21,'B̳ases'!$D$2:$D$296,"<"&DATE(YEAR(B21),MONTH(B21)+1,1),'B̳ases'!$C$2:$C$296,$C$4,'B̳ases'!$G$2:$G$296,$C$5,'B̳ases'!$E$2:$E$296,$C$6) -> 31 | J21: =IF(AND(OR($B$4="Todos",'B̳ases'!$C10=$B$4),OR($B$5="Todos",'B̳ases'!$G10=$C$5),OR($B$6="Todos",'B̳ases'!$E10=$C$6)),'B̳ases'!$M10+ROW()/1000000,"") -> 60.000021
A22: Abr | B22: =DATE($B$8,4,1) -> 04/2024 | C22: =SUMIFS('B̳ases'!$M$2:$M$296,'B̳ases'!$D$2:$D$296,">="&B22,'B̳ases'!$D$2:$D$296,"<"&DATE(YEAR(B22),MONTH(B22)+1,1),'B̳ases'!$C$2:$C$296,$C$4,'B̳ases'!$G$2:$G$296,$C$5,'B̳ases'!$E$2:$E$296,$C$6) -> R$ 782 | D22: =COUNTIFS('B̳ases'!$D$2:$D$296,">="&B22,'B̳ases'!$D$2:$D$296,"<"&DATE(YEAR(B22),MONTH(B22)+1,1),'B̳ases'!$C$2:$C$296,$C$4,'B̳ases'!$G$2:$G$296,$C$5,'B̳ases'!$E$2:$E$296,$C$6) -> 30 | J22: =IF(AND(OR($B$4="Todos",'B̳ases'!$C11=$B$4),OR($B$5="Todos",'B̳ases'!$G11=$C$5),OR($B$6="Todos",'B̳ases'!$E11=$C$6)),'B̳ases'!$M11+ROW()/1000000,"") -> 15.000022
A23: Mai | B23: =DATE($B$8,5,1) -> 05/2024 | C23: =SUMIFS('B̳ases'!$M$2:$M$296,'B̳ases'!$D$2:$D$296,">="&B23,'B̳ases'!$D$2:$D$296,"<"&DATE(YEAR(B23),MONTH(B23)+1,1),'B̳ases'!$C$2:$C$296,$C$4,'B̳ases'!$G$2:$G$296,$C$5,'B̳ases'!$E$2:$E$296,$C$6) -> R$ 777 | D23: =COUNTIFS('B̳ases'!$D$2:$D$296,">="&B23,'B̳ases'!$D$2:$D$296,"<"&DATE(YEAR(B23),MONTH(B23)+1,1),'B̳ases'!$C$2:$C$296,$C$4,'B̳ases'!$G$2:$G$296,$C$5,'B̳ases'!$E$2:$E$296,$C$6) -> 31 | J23: =IF(AND(OR($B$4="Todos",'B̳ases'!$C12=$B$4),OR($B$5="Todos",'B̳ases'!$G12=$C$5),OR($B$6="Todos",'B̳ases'!$E12=$C$6)),'B̳ases'!$M12+ROW()/1000000,"") -> 4.000023
A24: Jun | B24: =DATE($B$8,6,1) -> 06/2024 | C24: =SUMIFS('B̳ases'!$M$2:$M$296,'B̳ases'!$D$2:$D$296,">="&B24,'B̳ases'!$D$2:$D$296,"<"&DATE(YEAR(B24),MONTH(B24)+1,1),'B̳ases'!$C$2:$C$296,$C$4,'B̳ases'!$G$2:$G$296,$C$5,'B̳ases'!$E$2:$E$296,$C$6) -> R$ 770 | D24: =COUNTIFS('B̳ases'!$D$2:$D$296,">="&B24,'B̳ases'!$D$2:$D$296,"<"&DATE(YEAR(B24),MONTH(B24)+1,1),'B̳ases'!$C$2:$C$296,$C$4,'B̳ases'!$G$2:$G$296,$C$5,'B̳ases'!$E$2:$E$296,$C$6) -> 30 | J24: =IF(AND(OR($B$4="Todos",'B̳ases'!$C13=$B$4),OR($B$5="Todos",'B̳ases'!$G13=$C$5),OR($B$6="Todos",'B̳ases'!$E13=$C$6)),'B̳ases'!$M13+ROW()/1000000,"") -> 45.000024
A25: Jul | B25: =DATE($B$8,7,1) -> 07/2024 | C25: =SUMIFS('B̳ases'!$M$2:$M$296,'B̳ases'!$D$2:$D$296,">="&B25,'B̳ases'!$D$2:$D$296,"<"&DATE(YEAR(B25),MONTH(B25)+1,1),'B̳ases'!$C$2:$C$296,$C$4,'B̳ases'!$G$2:$G$296,$C$5,'B̳ases'!$E$2:$E$296,$C$6) -> R$ 784 | D25: =COUNTIFS('B̳ases'!$D$2:$D$296,">="&B25,'B̳ases'!$D$2:$D$296,"<"&DATE(YEAR(B25),MONTH(B25)+1,1),'B̳ases'!$C$2:$C$296,$C$4,'B̳ases'!$G$2:$G$296,$C$5,'B̳ases'!$E$2:$E$296,$C$6) -> 31 | J25: =IF(AND(OR($B$4="Todos",'B̳ases'!$C14=$B$4),OR($B$5="Todos",'B̳ases'!$G14=$C$5),OR($B$6="Todos",'B̳ases'!$E14=$C$6)),'B̳ases'!$M14+ROW()/1000000,"") -> 20.000025
A26: Ago | B26: =DATE($B$8,8,1) -> 08/2024 | C26: =SUMIFS('B̳ases'!$M$2:$M$296,'B̳ases'!$D$2:$D$296,">="&B26,'B̳ases'!$D$2:$D$296,"<"&DATE(YEAR(B26),MONTH(B26)+1,1),'B̳ases'!$C$2:$C$296,$C$4,'B̳ases'!$G$2:$G$296,$C$5,'B̳ases'!$E$2:$E$296,$C$6) -> R$ 787 | D26: =COUNTIFS('B̳ases'!$D$2:$D$296,">="&B26,'B̳ases'!$D$2:$D$296,"<"&DATE(YEAR(B26),MONTH(B26)+1,1),'B̳ases'!$C$2:$C$296,$C$4,'B̳ases'!$G$2:$G$296,$C$5,'B̳ases'!$E$2:$E$296,$C$6) -> 31 | J26: =IF(AND(OR($B$4="Todos",'B̳ases'!$C15=$B$4),OR($B$5="Todos",'B̳ases'!$G15=$C$5),OR($B$6="Todos",'B̳ases'!$E15=$C$6)),'B̳ases'!$M15+ROW()/1000000,"") -> 5.000026
A27: Set | B27: =DATE($B$8,9,1) -> 09/2024 | C27: =SUMIFS('B̳ases'!$M$2:$M$296,'B̳ases'!$D$2:$D$296,">="&B27,'B̳ases'!$D$2:$D$296,"<"&DATE(YEAR(B27),MONTH(B27)+1,1),'B̳ases'!$C$2:$C$296,$C$4,'B̳ases'!$G$2:$G$296,$C$5,'B̳ases'!$E$2:$E$296,$C$6) -> R$ 780 | D27: =COUNTIFS('B̳ases'!$D$2:$D$296,">="&B27,'B̳ases'!$D$2:$D$296,"<"&DATE(YEAR(B27),MONTH(B27)+1,1),'B̳ases'!$C$2:$C$296,$C$4,'B̳ases'!$G$2:$G$296,$C$5,'B̳ases'!$E$2:$E$296,$C$6) -> 30 | J27: =IF(AND(OR($B$4="Todos",'B̳ases'!$C16=$B$4),OR($B$5="Todos",'B̳ases'!$G16=$C$5),OR($B$6="Todos",'B̳ases'!$E16=$C$6)),'B̳ases'!$M16+ROW()/1000000,"") -> 57.000027
A28: Out | B28: =DATE($B$8,10,1) -> 10/2024 | C28: =SUMIFS('B̳ases'!$M$2:$M$296,'B̳ases'!$D$2:$D$296,">="&B28,'B̳ases'!$D$2:$D$296,"<"&DATE(YEAR(B28),MONTH(B28)+1,1),'B̳ases'!$C$2:$C$296,$C$4,'B̳ases'!$G$2:$G$296,$C$5,'B̳ases'!$E$2:$E$296,$C$6) -> R$ 832 | D28: =COUNTIFS('B̳ases'!$D$2:$D$296,">="&B28,'B̳ases'!$D$2:$D$296,"<"&DATE(YEAR(B28),MONTH(B28)+1,1),'B̳ases'!$C$2:$C$296,$C$4,'B̳ases'!$G$2:$G$296,$C$5,'B̳ases'!$E$2:$E$296,$C$6) -> 31 | J28: =IF(AND(OR($B$4="Todos",'B̳ases'!$C17=$B$4),OR($B$5="Todos",'B̳ases'!$G17=$C$5),OR($B$6="Todos",'B̳ases'!$E17=$C$6)),'B̳ases'!$M17+ROW()/1000000,"") -> 18.000028
A29: Nov | B29: =DATE($B$8,11,1) -> 11/2024 | C29: =SUMIFS('B̳ases'!$M$2:$M$296,'B̳ases'!$D$2:$D$296,">="&B29,'B̳ases'!$D$2:$D$296,"<"&DATE(YEAR(B29),MONTH(B29)+1,1),'B̳ases'!$C$2:$C$296,$C$4,'B̳ases'!$G$2:$G$296,$C$5,'B̳ases'!$E$2:$E$296,$C$6) -> R$ 784 | D29: =COUNTIFS('B̳ases'!$D$2:$D$296,">="&B29,'B̳ases'!$D$2:$D$296,"<"&DATE(YEAR(B29),MONTH(B29)+1,1),'B̳ases'!$C$2:$C$296,$C$4,'B̳ases'!$G$2:$G$296,$C$5,'B̳ases'!$E$2:$E$296,$C$6) -> 30 | J29: =IF(AND(OR($B$4="Todos",'B̳ases'!$C18=$B$4),OR($B$5="Todos",'B̳ases'!$G18=$C$5),OR($B$6="Todos",'B̳ases'!$E18=$C$6)),'B̳ases'!$M18+ROW()/1000000,"") -> 3.000029
A30: Dez | B30: =DATE($B$8,12,1) -> 12/2024 | C30: =SUMIFS('B̳ases'!$M$2:$M$296,'B̳ases'!$D$2:$D$296,">="&B30,'B̳ases'!$D$2:$D$296,"<"&DATE(YEAR(B30),MONTH(B30)+1,1),'B̳ases'!$C$2:$C$296,$C$4,'B̳ases'!$G$2:$G$296,$C$5,'B̳ases'!$E$2:$E$296,$C$6) -> R$ 389 | D30: =COUNTIFS('B̳ases'!$D$2:$D$296,">="&B30,'B̳ases'!$D$2:$D$296,"<"&DATE(YEAR(B30),MONTH(B30)+1,1),'B̳ases'!$C$2:$C$296,$C$4,'B̳ases'!$G$2:$G$296,$C$5,'B̳ases'!$E$2:$E$296,$C$6) -> 16 | J30: =IF(AND(OR($B$4="Todos",'B̳ases'!$C19=$B$4),OR($B$5="Todos",'B̳ases'!$G19=$C$5),OR($B$6="Todos",'B̳ases'!$E19=$C$6)),'B̳ases'!$M19+ROW()/1000000,"") -> 58.000030
J31: =IF(AND(OR($B$4="Todos",'B̳ases'!$C20=$B$4),OR($B$5="Todos",'B̳ases'!$G20=$C$5),OR($B$6="Todos",'B̳ases'!$E20=$C$6)),'B̳ases'!$M20+ROW()/1000000,"") -> 25.000031
A32: T3 · Mix por tipo de assinatura (ignora o filtro de Tipo) | J32: =IF(AND(OR($B$4="Todos",'B̳ases'!$C21=$B$4),OR($B$5="Todos",'B̳ases'!$G21=$C$5),OR($B$6="Todos",'B̳ases'!$E21=$C$6)),'B̳ases'!$M21+ROW()/1000000,"") -> 5.000032
A33: Tipo | B33: Valor na base | C33: Assinantes | D33: Receita | J33: =IF(AND(OR($B$4="Todos",'B̳ases'!$C22=$B$4),OR($B$5="Todos",'B̳ases'!$G22=$C$5),OR($B$6="Todos",'B̳ases'!$E22=$C$6)),'B̳ases'!$M22+ROW()/1000000,"") -> 62.000033
A34: Mensal | B34: Monthly | C34: =COUNTIFS('B̳ases'!$G$2:$G$296,$B34,'B̳ases'!$C$2:$C$296,$C$4,'B̳ases'!$E$2:$E$296,$C$6) -> 139 | D34: =SUMIFS('B̳ases'!$M$2:$M$296,'B̳ases'!$G$2:$G$296,$B34,'B̳ases'!$C$2:$C$296,$C$4,'B̳ases'!$E$2:$E$296,$C$6) -> R$ 3,571 | J34: =IF(AND(OR($B$4="Todos",'B̳ases'!$C23=$B$4),OR($B$5="Todos",'B̳ases'!$G23=$C$5),OR($B$6="Todos",'B̳ases'!$E23=$C$6)),'B̳ases'!$M23+ROW()/1000000,"") -> 15.000034
A35: Trimestral | B35: Quarterly | C35: =COUNTIFS('B̳ases'!$G$2:$G$296,$B35,'B̳ases'!$C$2:$C$296,$C$4,'B̳ases'!$E$2:$E$296,$C$6) -> 85 | D35: =SUMIFS('B̳ases'!$M$2:$M$296,'B̳ases'!$G$2:$G$296,$B35,'B̳ases'!$C$2:$C$296,$C$4,'B̳ases'!$E$2:$E$296,$C$6) -> R$ 2,308 | J35: =IF(AND(OR($B$4="Todos",'B̳ases'!$C24=$B$4),OR($B$5="Todos",'B̳ases'!$G24=$C$5),OR($B$6="Todos",'B̳ases'!$E24=$C$6)),'B̳ases'!$M24+ROW()/1000000,"") -> 4.000035
A36: Anual | B36: Annual | C36: =COUNTIFS('B̳ases'!$G$2:$G$296,$B36,'B̳ases'!$C$2:$C$296,$C$4,'B̳ases'!$E$2:$E$296,$C$6) -> 71 | D36: =SUMIFS('B̳ases'!$M$2:$M$296,'B̳ases'!$G$2:$G$296,$B36,'B̳ases'!$C$2:$C$296,$C$4,'B̳ases'!$E$2:$E$296,$C$6) -> R$ 1,754 | J36: =IF(AND(OR($B$4="Todos",'B̳ases'!$C25=$B$4),OR($B$5="Todos",'B̳ases'!$G25=$C$5),OR($B$6="Todos",'B̳ases'!$E25=$C$6)),'B̳ases'!$M25+ROW()/1000000,"") -> 45.000036
J37: =IF(AND(OR($B$4="Todos",'B̳ases'!$C26=$B$4),OR($B$5="Todos",'B̳ases'!$G26=$C$5),OR($B$6="Todos",'B̳ases'!$E26=$C$6)),'B̳ases'!$M26+ROW()/1000000,"") -> 20.000037
A38: T4 · Renovação automática por plano (ignora Plano e Renovação) | J38: =IF(AND(OR($B$4="Todos",'B̳ases'!$C27=$B$4),OR($B$5="Todos",'B̳ases'!$G27=$C$5),OR($B$6="Todos",'B̳ases'!$E27=$C$6)),'B̳ases'!$M27+ROW()/1000000,"") -> 5.000038
A39: Plano | B39: Com renovação | C39: Sem renovação | J39: =IF(AND(OR($B$4="Todos",'B̳ases'!$C28=$B$4),OR($B$5="Todos",'B̳ases'!$G28=$C$5),OR($B$6="Todos",'B̳ases'!$E28=$C$6)),'B̳ases'!$M28+ROW()/1000000,"") -> 60.000039
A40: Core | B40: =COUNTIFS('B̳ases'!$C$2:$C$296,$A40,'B̳ases'!$E$2:$E$296,"Yes",'B̳ases'!$G$2:$G$296,$C$5) -> 51 | C40: =COUNTIFS('B̳ases'!$C$2:$C$296,$A40,'B̳ases'!$E$2:$E$296,"No",'B̳ases'!$G$2:$G$296,$C$5) -> 50 | J40: =IF(AND(OR($B$4="Todos",'B̳ases'!$C29=$B$4),OR($B$5="Todos",'B̳ases'!$G29=$C$5),OR($B$6="Todos",'B̳ases'!$E29=$C$6)),'B̳ases'!$M29+ROW()/1000000,"") -> 15.000040
A41: Standard | B41: =COUNTIFS('B̳ases'!$C$2:$C$296,$A41,'B̳ases'!$E$2:$E$296,"Yes",'B̳ases'!$G$2:$G$296,$C$5) -> 49 | C41: =COUNTIFS('B̳ases'!$C$2:$C$296,$A41,'B̳ases'!$E$2:$E$296,"No",'B̳ases'!$G$2:$G$296,$C$5) -> 47 | J41: =IF(AND(OR($B$4="Todos",'B̳ases'!$C30=$B$4),OR($B$5="Todos",'B̳ases'!$G30=$C$5),OR($B$6="Todos",'B̳ases'!$E30=$C$6)),'B̳ases'!$M30+ROW()/1000000,"") -> 4.000041
A42: Ultimate | B42: =COUNTIFS('B̳ases'!$C$2:$C$296,$A42,'B̳ases'!$E$2:$E$296,"Yes",'B̳ases'!$G$2:$G$296,$C$5) -> 48 | C42: =COUNTIFS('B̳ases'!$C$2:$C$296,$A42,'B̳ases'!$E$2:$E$296,"No",'B̳ases'!$G$2:$G$296,$C$5) -> 50 | J42: =IF(AND(OR($B$4="Todos",'B̳ases'!$C31=$B$4),OR($B$5="Todos",'B̳ases'!$G31=$C$5),OR($B$6="Todos",'B̳ases'!$E31=$C$6)),'B̳ases'!$M31+ROW()/1000000,"") -> 58.000042
J43: =IF(AND(OR($B$4="Todos",'B̳ases'!$C32=$B$4),OR($B$5="Todos",'B̳ases'!$G32=$C$5),OR($B$6="Todos",'B̳ases'!$E32=$C$6)),'B̳ases'!$M32+ROW()/1000000,"") -> 20.000043
A44: T5 · Adesão aos add-ons por plano (ignora o filtro de Plano) | J44: =IF(AND(OR($B$4="Todos",'B̳ases'!$C33=$B$4),OR($B$5="Todos",'B̳ases'!$G33=$C$5),OR($B$6="Todos",'B̳ases'!$E33=$C$6)),'B̳ases'!$M33+ROW()/1000000,"") -> 5.000044
A45: Plano | B45: % com Minecraft | C45: % com EA Play | D45: Assinantes | J45: =IF(AND(OR($B$4="Todos",'B̳ases'!$C34=$B$4),OR($B$5="Todos",'B̳ases'!$G34=$C$5),OR($B$6="Todos",'B̳ases'!$E34=$C$6)),'B̳ases'!$M34+ROW()/1000000,"") -> 62.000045
A46: Core | B46: =IFERROR(COUNTIFS('B̳ases'!$C$2:$C$296,$A46,'B̳ases'!$J$2:$J$296,"Yes",'B̳ases'!$G$2:$G$296,$C$5,'B̳ases'!$E$2:$E$296,$C$6)/D46,0) -> 0% | C46: =IFERROR(COUNTIFS('B̳ases'!$C$2:$C$296,$A46,'B̳ases'!$H$2:$H$296,"Yes",'B̳ases'!$G$2:$G$296,$C$5,'B̳ases'!$E$2:$E$296,$C$6)/D46,0) -> 0% | D46: =COUNTIFS('B̳ases'!$C$2:$C$296,$A46,'B̳ases'!$G$2:$G$296,$C$5,'B̳ases'!$E$2:$E$296,$C$6) -> 101 | J46: =IF(AND(OR($B$4="Todos",'B̳ases'!$C35=$B$4),OR($B$5="Todos",'B̳ases'!$G35=$C$5),OR($B$6="Todos",'B̳ases'!$E35=$C$6)),'B̳ases'!$M35+ROW()/1000000,"") -> 15.000046
A47: Standard | B47: =IFERROR(COUNTIFS('B̳ases'!$C$2:$C$296,$A47,'B̳ases'!$J$2:$J$296,"Yes",'B̳ases'!$G$2:$G$296,$C$5,'B̳ases'!$E$2:$E$296,$C$6)/D47,0) -> 100% | C47: =IFERROR(COUNTIFS('B̳ases'!$C$2:$C$296,$A47,'B̳ases'!$H$2:$H$296,"Yes",'B̳ases'!$G$2:$G$296,$C$5,'B̳ases'!$E$2:$E$296,$C$6)/D47,0) -> 0% | D47: =COUNTIFS('B̳ases'!$C$2:$C$296,$A47,'B̳ases'!$G$2:$G$296,$C$5,'B̳ases'!$E$2:$E$296,$C$6) -> 96 | J47: =IF(AND(OR($B$4="Todos",'B̳ases'!$C36=$B$4),OR($B$5="Todos",'B̳ases'!$G36=$C$5),OR($B$6="Todos",'B̳ases'!$E36=$C$6)),'B̳ases'!$M36+ROW()/1000000,"") -> 4.000047
A48: Ultimate | B48: =IFERROR(COUNTIFS('B̳ases'!$C$2:$C$296,$A48,'B̳ases'!$J$2:$J$296,"Yes",'B̳ases'!$G$2:$G$296,$C$5,'B̳ases'!$E$2:$E$296,$C$6)/D48,0) -> 100% | C48: =IFERROR(COUNTIFS('B̳ases'!$C$2:$C$296,$A48,'B̳ases'!$H$2:$H$296,"Yes",'B̳ases'!$G$2:$G$296,$C$5,'B̳ases'!$E$2:$E$296,$C$6)/D48,0) -> 100% | D48: =COUNTIFS('B̳ases'!$C$2:$C$296,$A48,'B̳ases'!$G$2:$G$296,$C$5,'B̳ases'!$E$2:$E$296,$C$6) -> 98 | J48: =IF(AND(OR($B$4="Todos",'B̳ases'!$C37=$B$4),OR($B$5="Todos",'B̳ases'!$G37=$C$5),OR($B$6="Todos",'B̳ases'!$E37=$C$6)),'B̳ases'!$M37+ROW()/1000000,"") -> 5.000048
J49: =IF(AND(OR($B$4="Todos",'B̳ases'!$C38=$B$4),OR($B$5="Todos",'B̳ases'!$G38=$C$5),OR($B$6="Todos",'B̳ases'!$E38=$C$6)),'B̳ases'!$M38+ROW()/1000000,"") -> 58.000049
A50: T6 · Indicadores (aplicam os filtros indicados) | J50: =IF(AND(OR($B$4="Todos",'B̳ases'!$C39=$B$4),OR($B$5="Todos",'B̳ases'!$G39=$C$5),OR($B$6="Todos",'B̳ases'!$E39=$C$6)),'B̳ases'!$M39+ROW()/1000000,"") -> 20.000050
A51: Indicador | B51: Valor | C51: Observação | J51: =IF(AND(OR($B$4="Todos",'B̳ases'!$C40=$B$4),OR($B$5="Todos",'B̳ases'!$G40=$C$5),OR($B$6="Todos",'B̳ases'!$E40=$C$6)),'B̳ases'!$M40+ROW()/1000000,"") -> 4.000051
A52: Receita total | B52: =SUMIFS('B̳ases'!$M$2:$M$296,'B̳ases'!$C$2:$C$296,$C$4,'B̳ases'!$G$2:$G$296,$C$5,'B̳ases'!$E$2:$E$296,$C$6) -> R$ 7,633 | C52: Soma de Total Value · todos os filtros | J52: =IF(AND(OR($B$4="Todos",'B̳ases'!$C41=$B$4),OR($B$5="Todos",'B̳ases'!$G41=$C$5),OR($B$6="Todos",'B̳ases'!$E41=$C$6)),'B̳ases'!$M41+ROW()/1000000,"") -> 50.000052
A53: Assinantes | B53: =COUNTIFS('B̳ases'!$C$2:$C$296,$C$4,'B̳ases'!$G$2:$G$296,$C$5,'B̳ases'!$E$2:$E$296,$C$6) -> 295 | C53: Todos os filtros | J53: =IF(AND(OR($B$4="Todos",'B̳ases'!$C42=$B$4),OR($B$5="Todos",'B̳ases'!$G42=$C$5),OR($B$6="Todos",'B̳ases'!$E42=$C$6)),'B̳ases'!$M42+ROW()/1000000,"") -> 25.000053
A54: Ticket médio | B54: =IFERROR(B52/B53,0) -> R$ 25.87 | C54: Receita ÷ assinantes | J54: =IF(AND(OR($B$4="Todos",'B̳ases'!$C43=$B$4),OR($B$5="Todos",'B̳ases'!$G43=$C$5),OR($B$6="Todos",'B̳ases'!$E43=$C$6)),'B̳ases'!$M43+ROW()/1000000,"") -> 5.000054
A55: Cupons concedidos | B55: =SUMIFS('B̳ases'!$L$2:$L$296,'B̳ases'!$C$2:$C$296,$C$4,'B̳ases'!$G$2:$G$296,$C$5,'B̳ases'!$E$2:$E$296,$C$6) -> R$ 2,122 | C55: Soma de Coupon Value | J55: =IF(AND(OR($B$4="Todos",'B̳ases'!$C44=$B$4),OR($B$5="Todos",'B̳ases'!$G44=$C$5),OR($B$6="Todos",'B̳ases'!$E44=$C$6)),'B̳ases'!$M44+ROW()/1000000,"") -> 45.000055
A56: Cupons sobre o valor bruto | B56: =IFERROR(B55/(B52+B55),0) -> 21.8% | C56: Cupom ÷ (receita + cupom) | J56: =IF(AND(OR($B$4="Todos",'B̳ases'!$C45=$B$4),OR($B$5="Todos",'B̳ases'!$G45=$C$5),OR($B$6="Todos",'B̳ases'!$E45=$C$6)),'B̳ases'!$M45+ROW()/1000000,"") -> 18.000056
A57: % com renovação automática | B57: =IFERROR(COUNTIFS('B̳ases'!$C$2:$C$296,$C$4,'B̳ases'!$G$2:$G$296,$C$5,'B̳ases'!$E$2:$E$296,$C$6,'B̳ases'!$E$2:$E$296,"Yes")/B53,0) -> 50.2% | C57: Auto Renewal = Yes | J57: =IF(AND(OR($B$4="Todos",'B̳ases'!$C46=$B$4),OR($B$5="Todos",'B̳ases'!$G46=$C$5),OR($B$6="Todos",'B̳ases'!$E46=$C$6)),'B̳ases'!$M46+ROW()/1000000,"") -> 3.000057
A58: Assinantes sem renovação automática | B58: =COUNTIFS('B̳ases'!$C$2:$C$296,$C$4,'B̳ases'!$G$2:$G$296,$C$5,'B̳ases'!$E$2:$E$296,"No") -> 147 | C58: Filtros de Plano e Tipo | J58: =IF(AND(OR($B$4="Todos",'B̳ases'!$C47=$B$4),OR($B$5="Todos",'B̳ases'!$G47=$C$5),OR($B$6="Todos",'B̳ases'!$E47=$C$6)),'B̳ases'!$M47+ROW()/1000000,"") -> 60.000058
A59: Receita desses assinantes | B59: =SUMIFS('B̳ases'!$M$2:$M$296,'B̳ases'!$C$2:$C$296,$C$4,'B̳ases'!$G$2:$G$296,$C$5,'B̳ases'!$E$2:$E$296,"No") -> R$ 3,847 | C59: Filtros de Plano e Tipo | J59: =IF(AND(OR($B$4="Todos",'B̳ases'!$C48=$B$4),OR($B$5="Todos",'B̳ases'!$G48=$C$5),OR($B$6="Todos",'B̳ases'!$E48=$C$6)),'B̳ases'!$M48+ROW()/1000000,"") -> 20.000059
A60: Assinantes no plano mensal | B60: =COUNTIFS('B̳ases'!$C$2:$C$296,$C$4,'B̳ases'!$G$2:$G$296,"Monthly",'B̳ases'!$E$2:$E$296,$C$6) -> 139 | C60: Filtros de Plano e Renovação | J60: =IF(AND(OR($B$4="Todos",'B̳ases'!$C49=$B$4),OR($B$5="Todos",'B̳ases'!$G49=$C$5),OR($B$6="Todos",'B̳ases'!$E49=$C$6)),'B̳ases'!$M49+ROW()/1000000,"") -> 5.000060
A61: Receita desses assinantes (mensal) | B61: =SUMIFS('B̳ases'!$M$2:$M$296,'B̳ases'!$C$2:$C$296,$C$4,'B̳ases'!$G$2:$G$296,"Monthly",'B̳ases'!$E$2:$E$296,$C$6) -> R$ 3,571 | C61: Filtros de Plano e Renovação | J61: =IF(AND(OR($B$4="Todos",'B̳ases'!$C50=$B$4),OR($B$5="Todos",'B̳ases'!$G50=$C$5),OR($B$6="Todos",'B̳ases'!$E50=$C$6)),'B̳ases'!$M50+ROW()/1000000,"") -> 62.000061
J62: =IF(AND(OR($B$4="Todos",'B̳ases'!$C51=$B$4),OR($B$5="Todos",'B̳ases'!$G51=$C$5),OR($B$6="Todos",'B̳ases'!$E51=$C$6)),'B̳ases'!$M51+ROW()/1000000,"") -> 15.000062
A63: T7 · Receita por plano × tipo (aplica filtro de Renovação) | J63: =IF(AND(OR($B$4="Todos",'B̳ases'!$C52=$B$4),OR($B$5="Todos",'B̳ases'!$G52=$C$5),OR($B$6="Todos",'B̳ases'!$E52=$C$6)),'B̳ases'!$M52+ROW()/1000000,"") -> 4.000063
A64: Valor na base | B64: Monthly | C64: Quarterly | D64: Annual | J64: =IF(AND(OR($B$4="Todos",'B̳ases'!$C53=$B$4),OR($B$5="Todos",'B̳ases'!$G53=$C$5),OR($B$6="Todos",'B̳ases'!$E53=$C$6)),'B̳ases'!$M53+ROW()/1000000,"") -> 58.000064
A65: Plano | B65: Mensal | C65: Trimestral | D65: Anual | E65: Total | J65: =IF(AND(OR($B$4="Todos",'B̳ases'!$C54=$B$4),OR($B$5="Todos",'B̳ases'!$G54=$C$5),OR($B$6="Todos",'B̳ases'!$E54=$C$6)),'B̳ases'!$M54+ROW()/1000000,"") -> 20.000065
A66: Core | B66: =SUMIFS('B̳ases'!$M$2:$M$296,'B̳ases'!$C$2:$C$296,$A66,'B̳ases'!$G$2:$G$296,B$64,'B̳ases'!$E$2:$E$296,$C$6) -> R$ 192 | C66: =SUMIFS('B̳ases'!$M$2:$M$296,'B̳ases'!$C$2:$C$296,$A66,'B̳ases'!$G$2:$G$296,C$64,'B̳ases'!$E$2:$E$296,$C$6) -> R$ 132 | D66: =SUMIFS('B̳ases'!$M$2:$M$296,'B̳ases'!$C$2:$C$296,$A66,'B̳ases'!$G$2:$G$296,D$64,'B̳ases'!$E$2:$E$296,$C$6) -> R$ 120 | E66: =SUM(B66:D66) -> R$ 444 | J66: =IF(AND(OR($B$4="Todos",'B̳ases'!$C55=$B$4),OR($B$5="Todos",'B̳ases'!$G55=$C$5),OR($B$6="Todos",'B̳ases'!$E55=$C$6)),'B̳ases'!$M55+ROW()/1000000,"") -> 5.000066
A67: Standard | B67: =SUMIFS('B̳ases'!$M$2:$M$296,'B̳ases'!$C$2:$C$296,$A67,'B̳ases'!$G$2:$G$296,B$64,'B̳ases'!$E$2:$E$296,$C$6) -> R$ 958 | C67: =SUMIFS('B̳ases'!$M$2:$M$296,'B̳ases'!$C$2:$C$296,$A67,'B̳ases'!$G$2:$G$296,C$64,'B̳ases'!$E$2:$E$296,$C$6) -> R$ 395 | D67: =SUMIFS('B̳ases'!$M$2:$M$296,'B̳ases'!$C$2:$C$296,$A67,'B̳ases'!$G$2:$G$296,D$64,'B̳ases'!$E$2:$E$296,$C$6) -> R$ 448 | E67: =SUM(B67:D67) -> R$ 1,801 | J67: =IF(AND(OR($B$4="Todos",'B̳ases'!$C56=$B$4),OR($B$5="Todos",'B̳ases'!$G56=$C$5),OR($B$6="Todos",'B̳ases'!$E56=$C$6)),'B̳ases'!$M56+ROW()/1000000,"") -> 45.000067
A68: Ultimate | B68: =SUMIFS('B̳ases'!$M$2:$M$296,'B̳ases'!$C$2:$C$296,$A68,'B̳ases'!$G$2:$G$296,B$64,'B̳ases'!$E$2:$E$296,$C$6) -> R$ 2,421 | C68: =SUMIFS('B̳ases'!$M$2:$M$296,'B̳ases'!$C$2:$C$296,$A68,'B̳ases'!$G$2:$G$296,C$64,'B̳ases'!$E$2:$E$296,$C$6) -> R$ 1,781 | D68: =SUMIFS('B̳ases'!$M$2:$M$296,'B̳ases'!$C$2:$C$296,$A68,'B̳ases'!$G$2:$G$296,D$64,'B̳ases'!$E$2:$E$296,$C$6) -> R$ 1,186 | E68: =SUM(B68:D68) -> R$ 5,388 | J68: =IF(AND(OR($B$4="Todos",'B̳ases'!$C57=$B$4),OR($B$5="Todos",'B̳ases'!$G57=$C$5),OR($B$6="Todos",'B̳ases'!$E57=$C$6)),'B̳ases'!$M57+ROW()/1000000,"") -> 15.000068
A69: Total | B69: =SUM(B66:B68) -> R$ 3,571 | C69: =SUM(C66:C68) -> R$ 2,308 | D69: =SUM(D66:D68) -> R$ 1,754 | E69: =SUM(E66:E68) -> R$ 7,633 | J69: =IF(AND(OR($B$4="Todos",'B̳ases'!$C58=$B$4),OR($B$5="Todos",'B̳ases'!$G58=$C$5),OR($B$6="Todos",'B̳ases'!$E58=$C$6)),'B̳ases'!$M58+ROW()/1000000,"") -> 4.000069
J70: =IF(AND(OR($B$4="Todos",'B̳ases'!$C59=$B$4),OR($B$5="Todos",'B̳ases'!$G59=$C$5),OR($B$6="Todos",'B̳ases'!$E59=$C$6)),'B̳ases'!$M59+ROW()/1000000,"") -> 62.000070
A71: T8 · Top 10 assinantes por valor (aplica todos os filtros) | J71: =IF(AND(OR($B$4="Todos",'B̳ases'!$C60=$B$4),OR($B$5="Todos",'B̳ases'!$G60=$C$5),OR($B$6="Todos",'B̳ases'!$E60=$C$6)),'B̳ases'!$M60+ROW()/1000000,"") -> 20.000071
A72: Posição | B72: Chave de ranking | C72: Linha na base | D72: Assinante | E72: Plano | F72: Tipo | G72: Valor | J72: =IF(AND(OR($B$4="Todos",'B̳ases'!$C61=$B$4),OR($B$5="Todos",'B̳ases'!$G61=$C$5),OR($B$6="Todos",'B̳ases'!$E61=$C$6)),'B̳ases'!$M61+ROW()/1000000,"") -> 5.000072
A73: 1 | B73: =IFERROR(LARGE($J$13:$J$307,A73),"") -> 62.000305 | C73: =IF(B73="","",MATCH(B73,$J$13:$J$307,0)) -> 293 | D73: {=IF(C73="","",INDEX('B̳ases'!$B$2:$B$296,C73))} -> Carla Siqueira | E73: {=IF(C73="","",INDEX('B̳ases'!$C$2:$C$296,C73))} -> Ultimate | F73: {=IF(C73="","",IFERROR(INDEX($A$34:$A$36,MATCH(INDEX('B̳ases'!$G$2:$G$296,C73),$B$34:$B$36,0)),INDEX('B̳ases'!$G$2:$G$296,C73)))} -> Mensal | G73: {=IF(C73="","",INDEX('B̳ases'!$M$2:$M$296,C73))} -> R$ 62 | J73: =IF(AND(OR($B$4="Todos",'B̳ases'!$C62=$B$4),OR($B$5="Todos",'B̳ases'!$G62=$C$5),OR($B$6="Todos",'B̳ases'!$E62=$C$6)),'B̳ases'!$M62+ROW()/1000000,"") -> 60.000073
A74: 2 | B74: =IFERROR(LARGE($J$13:$J$307,A74),"") -> 62.000290 | C74: =IF(B74="","",MATCH(B74,$J$13:$J$307,0)) -> 278 | D74: {=IF(C74="","",INDEX('B̳ases'!$B$2:$B$296,C74))} -> Natália Castro | E74: {=IF(C74="","",INDEX('B̳ases'!$C$2:$C$296,C74))} -> Ultimate | F74: {=IF(C74="","",IFERROR(INDEX($A$34:$A$36,MATCH(INDEX('B̳ases'!$G$2:$G$296,C74),$B$34:$B$36,0)),INDEX('B̳ases'!$G$2:$G$296,C74)))} -> Anual | G74: {=IF(C74="","",INDEX('B̳ases'!$M$2:$M$296,C74))} -> R$ 62 | J74: =IF(AND(OR($B$4="Todos",'B̳ases'!$C63=$B$4),OR($B$5="Todos",'B̳ases'!$G63=$C$5),OR($B$6="Todos",'B̳ases'!$E63=$C$6)),'B̳ases'!$M63+ROW()/1000000,"") -> 15.000074
A75: 3 | B75: =IFERROR(LARGE($J$13:$J$307,A75),"") -> 62.000281 | C75: =IF(B75="","",MATCH(B75,$J$13:$J$307,0)) -> 269 | D75: {=IF(C75="","",INDEX('B̳ases'!$B$2:$B$296,C75))} -> Elisa Correia | E75: {=IF(C75="","",INDEX('B̳ases'!$C$2:$C$296,C75))} -> Ultimate | F75: {=IF(C75="","",IFERROR(INDEX($A$34:$A$36,MATCH(INDEX('B̳ases'!$G$2:$G$296,C75),$B$34:$B$36,0)),INDEX('B̳ases'!$G$2:$G$296,C75)))} -> Mensal | G75: {=IF(C75="","",INDEX('B̳ases'!$M$2:$M$296,C75))} -> R$ 62 | J75: =IF(AND(OR($B$4="Todos",'B̳ases'!$C64=$B$4),OR($B$5="Todos",'B̳ases'!$G64=$C$5),OR($B$6="Todos",'B̳ases'!$E64=$C$6)),'B̳ases'!$M64+ROW()/1000000,"") -> 4.000075
A76: 4 | B76: =IFERROR(LARGE($J$13:$J$307,A76),"") -> 62.000264 | C76: =IF(B76="","",MATCH(B76,$J$13:$J$307,0)) -> 252 | D76: {=IF(C76="","",INDEX('B̳ases'!$B$2:$B$296,C76))} -> Natália Soares | E76: {=IF(C76="","",INDEX('B̳ases'!$C$2:$C$296,C76))} -> Ultimate | F76: {=IF(C76="","",IFERROR(INDEX($A$34:$A$36,MATCH(INDEX('B̳ases'!$G$2:$G$296,C76),$B$34:$B$36,0)),INDEX('B̳ases'!$G$2:$G$296,C76)))} -> Anual | G76: {=IF(C76="","",INDEX('B̳ases'!$M$2:$M$296,C76))} -> R$ 62 | J76: =IF(AND(OR($B$4="Todos",'B̳ases'!$C65=$B$4),OR($B$5="Todos",'B̳ases'!$G65=$C$5),OR($B$6="Todos",'B̳ases'!$E65=$C$6)),'B̳ases'!$M65+ROW()/1000000,"") -> 45.000076
A77: 5 | B77: =IFERROR(LARGE($J$13:$J$307,A77),"") -> 62.000255 | C77: =IF(B77="","",MATCH(B77,$J$13:$J$307,0)) -> 243 | D77: {=IF(C77="","",INDEX('B̳ases'!$B$2:$B$296,C77))} -> Elisa Neves | E77: {=IF(C77="","",INDEX('B̳ases'!$C$2:$C$296,C77))} -> Ultimate | F77: {=IF(C77="","",IFERROR(INDEX($A$34:$A$36,MATCH(INDEX('B̳ases'!$G$2:$G$296,C77),$B$34:$B$36,0)),INDEX('B̳ases'!$G$2:$G$296,C77)))} -> Mensal | G77: {=IF(C77="","",INDEX('B̳ases'!$M$2:$M$296,C77))} -> R$ 62 | J77: =IF(AND(OR($B$4="Todos",'B̳ases'!$C66=$B$4),OR($B$5="Todos",'B̳ases'!$G66=$C$5),OR($B$6="Todos",'B̳ases'!$E66=$C$6)),'B̳ases'!$M66+ROW()/1000000,"") -> 25.000077
A78: 6 | B78: =IFERROR(LARGE($J$13:$J$307,A78),"") -> 62.000240 | C78: =IF(B78="","",MATCH(B78,$J$13:$J$307,0)) -> 228 | D78: {=IF(C78="","",INDEX('B̳ases'!$B$2:$B$296,C78))} -> Patrícia Leite | E78: {=IF(C78="","",INDEX('B̳ases'!$C$2:$C$296,C78))} -> Ultimate | F78: {=IF(C78="","",IFERROR(INDEX($A$34:$A$36,MATCH(INDEX('B̳ases'!$G$2:$G$296,C78),$B$34:$B$36,0)),INDEX('B̳ases'!$G$2:$G$296,C78)))} -> Anual | G78: {=IF(C78="","",INDEX('B̳ases'!$M$2:$M$296,C78))} -> R$ 62 | J78: =IF(AND(OR($B$4="Todos",'B̳ases'!$C67=$B$4),OR($B$5="Todos",'B̳ases'!$G67=$C$5),OR($B$6="Todos",'B̳ases'!$E67=$C$6)),'B̳ases'!$M67+ROW()/1000000,"") -> 5.000078
A79: 7 | B79: =IFERROR(LARGE($J$13:$J$307,A79),"") -> 62.000231 | C79: =IF(B79="","",MATCH(B79,$J$13:$J$307,0)) -> 219 | D79: {=IF(C79="","",INDEX('B̳ases'!$B$2:$B$296,C79))} -> Gabriel Santos | E79: {=IF(C79="","",INDEX('B̳ases'!$C$2:$C$296,C79))} -> Ultimate | F79: {=IF(C79="","",IFERROR(INDEX($A$34:$A$36,MATCH(INDEX('B̳ases'!$G$2:$G$296,C79),$B$34:$B$36,0)),INDEX('B̳ases'!$G$2:$G$296,C79)))} -> Mensal | G79: {=IF(C79="","",INDEX('B̳ases'!$M$2:$M$296,C79))} -> R$ 62 | J79: =IF(AND(OR($B$4="Todos",'B̳ases'!$C68=$B$4),OR($B$5="Todos",'B̳ases'!$G68=$C$5),OR($B$6="Todos",'B̳ases'!$E68=$C$6)),'B̳ases'!$M68+ROW()/1000000,"") -> 58.000079
A80: 8 | B80: =IFERROR(LARGE($J$13:$J$307,A80),"") -> 62.000210 | C80: =IF(B80="","",MATCH(B80,$J$13:$J$307,0)) -> 198 | D80: {=IF(C80="","",INDEX('B̳ases'!$B$2:$B$296,C80))} -> Joana Silveira | E80: {=IF(C80="","",INDEX('B̳ases'!$C$2:$C$296,C80))} -> Ultimate | F80: {=IF(C80="","",IFERROR(INDEX($A$34:$A$36,MATCH(INDEX('B̳ases'!$G$2:$G$296,C80),$B$34:$B$36,0)),INDEX('B̳ases'!$G$2:$G$296,C80)))} -> Anual | G80: {=IF(C80="","",INDEX('B̳ases'!$M$2:$M$296,C80))} -> R$ 62 | J80: =IF(AND(OR($B$4="Todos",'B̳ases'!$C69=$B$4),OR($B$5="Todos",'B̳ases'!$G69=$C$5),OR($B$6="Todos",'B̳ases'!$E69=$C$6)),'B̳ases'!$M69+ROW()/1000000,"") -> 20.000080
A81: 9 | B81: =IFERROR(LARGE($J$13:$J$307,A81),"") -> 62.000201 | C81: =IF(B81="","",MATCH(B81,$J$13:$J$307,0)) -> 189 | D81: {=IF(C81="","",INDEX('B̳ases'!$B$2:$B$296,C81))} -> André Lopes | E81: {=IF(C81="","",INDEX('B̳ases'!$C$2:$C$296,C81))} -> Ultimate | F81: {=IF(C81="","",IFERROR(INDEX($A$34:$A$36,MATCH(INDEX('B̳ases'!$G$2:$G$296,C81),$B$34:$B$36,0)),INDEX('B̳ases'!$G$2:$G$296,C81)))} -> Mensal | G81: {=IF(C81="","",INDEX('B̳ases'!$M$2:$M$296,C81))} -> R$ 62 | J81: =IF(AND(OR($B$4="Todos",'B̳ases'!$C70=$B$4),OR($B$5="Todos",'B̳ases'!$G70=$C$5),OR($B$6="Todos",'B̳ases'!$E70=$C$6)),'B̳ases'!$M70+ROW()/1000000,"") -> 4.000081
A82: 10 | B82: =IFERROR(LARGE($J$13:$J$307,A82),"") -> 62.000185 | C82: =IF(B82="","",MATCH(B82,$J$13:$J$307,0)) -> 173 | D82: {=IF(C82="","",INDEX('B̳ases'!$B$2:$B$296,C82))} -> João Carvalho | E82: {=IF(C82="","",INDEX('B̳ases'!$C$2:$C$296,C82))} -> Ultimate | F82: {=IF(C82="","",IFERROR(INDEX($A$34:$A$36,MATCH(INDEX('B̳ases'!$G$2:$G$296,C82),$B$34:$B$36,0)),INDEX('B̳ases'!$G$2:$G$296,C82)))} -> Mensal | G82: {=IF(C82="","",INDEX('B̳ases'!$M$2:$M$296,C82))} -> R$ 62 | J82: =IF(AND(OR($B$4="Todos",'B̳ases'!$C71=$B$4),OR($B$5="Todos",'B̳ases'!$G71=$C$5),OR($B$6="Todos",'B̳ases'!$E71=$C$6)),'B̳ases'!$M71+ROW()/1000000,"") -> 50.000082
J83: =IF(AND(OR($B$4="Todos",'B̳ases'!$C72=$B$4),OR($B$5="Todos",'B̳ases'!$G72=$C$5),OR($B$6="Todos",'B̳ases'!$E72=$C$6)),'B̳ases'!$M72+ROW()/1000000,"") -> 25.000083
J84: =IF(AND(OR($B$4="Todos",'B̳ases'!$C73=$B$4),OR($B$5="Todos",'B̳ases'!$G73=$C$5),OR($B$6="Todos",'B̳ases'!$E73=$C$6)),'B̳ases'!$M73+ROW()/1000000,"") -> 5.000084
J85: =IF(AND(OR($B$4="Todos",'B̳ases'!$C74=$B$4),OR($B$5="Todos",'B̳ases'!$G74=$C$5),OR($B$6="Todos",'B̳ases'!$E74=$C$6)),'B̳ases'!$M74+ROW()/1000000,"") -> 45.000085
J86: =IF(AND(OR($B$4="Todos",'B̳ases'!$C75=$B$4),OR($B$5="Todos",'B̳ases'!$G75=$C$5),OR($B$6="Todos",'B̳ases'!$E75=$C$6)),'B̳ases'!$M75+ROW()/1000000,"") -> 18.000086
J87: =IF(AND(OR($B$4="Todos",'B̳ases'!$C76=$B$4),OR($B$5="Todos",'B̳ases'!$G76=$C$5),OR($B$6="Todos",'B̳ases'!$E76=$C$6)),'B̳ases'!$M76+ROW()/1000000,"") -> 3.000087
J88: =IF(AND(OR($B$4="Todos",'B̳ases'!$C77=$B$4),OR($B$5="Todos",'B̳ases'!$G77=$C$5),OR($B$6="Todos",'B̳ases'!$E77=$C$6)),'B̳ases'!$M77+ROW()/1000000,"") -> 60.000088
J89: =IF(AND(OR($B$4="Todos",'B̳ases'!$C78=$B$4),OR($B$5="Todos",'B̳ases'!$G78=$C$5),OR($B$6="Todos",'B̳ases'!$E78=$C$6)),'B̳ases'!$M78+ROW()/1000000,"") -> 20.000089
J90: =IF(AND(OR($B$4="Todos",'B̳ases'!$C79=$B$4),OR($B$5="Todos",'B̳ases'!$G79=$C$5),OR($B$6="Todos",'B̳ases'!$E79=$C$6)),'B̳ases'!$M79+ROW()/1000000,"") -> 5.000090
J91: =IF(AND(OR($B$4="Todos",'B̳ases'!$C80=$B$4),OR($B$5="Todos",'B̳ases'!$G80=$C$5),OR($B$6="Todos",'B̳ases'!$E80=$C$6)),'B̳ases'!$M80+ROW()/1000000,"") -> 62.000091
J92: =IF(AND(OR($B$4="Todos",'B̳ases'!$C81=$B$4),OR($B$5="Todos",'B̳ases'!$G81=$C$5),OR($B$6="Todos",'B̳ases'!$E81=$C$6)),'B̳ases'!$M81+ROW()/1000000,"") -> 15.000092
J93: =IF(AND(OR($B$4="Todos",'B̳ases'!$C82=$B$4),OR($B$5="Todos",'B̳ases'!$G82=$C$5),OR($B$6="Todos",'B̳ases'!$E82=$C$6)),'B̳ases'!$M82+ROW()/1000000,"") -> 4.000093
J94: =IF(AND(OR($B$4="Todos",'B̳ases'!$C83=$B$4),OR($B$5="Todos",'B̳ases'!$G83=$C$5),OR($B$6="Todos",'B̳ases'!$E83=$C$6)),'B̳ases'!$M83+ROW()/1000000,"") -> 58.000094
... J307: =IF(AND(OR($B$4="Todos",'B̳ases'!$C296=$B$4),OR($B$5="Todos",'B̳ases'!$G296=$C$5),OR($B$6="Todos",'B̳ases'!$E296=$C$6)),'B̳ases'!$M296+ROW()/1000000,"") -> 4.000307

Sheet D̳ashboard
E2: Dashboard de Vendas · Assinaturas
E3: ="Período da base: "&TEXT(MIN('B̳ases'!$D$2:$D$296),"dd/mm/yyyy")&" a "&TEXT(MAX('B̳ases'!$D$2:$D$296),"dd/mm/yyyy")&" · "&TEXT(COUNTA('B̳ases'!$A$2:$A$296),"#,##0")&" assinaturas" -> Período da base: 01/01/2024 a 16/12/2024 · 295 assinaturas
B6: PLANO | E6: TIPO DE ASSINATURA | H6: RENOVAÇÃO AUTOMÁTICA
B7: Todos | E7: Todos | H7: Todos | K7: ◄ Escolha nos filtros: indicadores e gráficos atualizam sozinhos.
B9: RECEITA TOTAL | E9: ASSINANTES | H9: TICKET MÉDIO | K9: CUPONS CONCEDIDOS | N9: RENOVAÇÃO AUTOMÁTICA
B10: ='C̳álculos'!B52 -> R$ 7,633 | E10: ='C̳álculos'!B53 -> 295 | H10: ='C̳álculos'!B54 -> R$ 25.87 | K10: ='C̳álculos'!B55 -> R$ 2,122 | N10: ='C̳álculos'!B57 -> 50.2%
B12: ="soma do valor total das assinaturas" -> soma do valor total das assinaturas | E12: ="assinaturas na seleção" -> assinaturas na seleção | H12: ="receita ÷ assinantes" -> receita ÷ assinantes | K12: =TEXT('C̳álculos'!B56,"0%")&" do valor bruto" -> 22% do valor bruto | N12: ="assinaturas com renovação ativa" -> assinaturas com renovação ativa
G46: Top 10 assinantes por valor
G47: # | H47: Assinante | K47: Plano | M47: Tipo | O47: Valor total
G48: =IF('C̳álculos'!D73="","",1) -> 1 | H48: ='C̳álculos'!D73 -> Carla Siqueira | K48: ='C̳álculos'!E73 -> Ultimate | M48: ='C̳álculos'!F73 -> Mensal | O48: ='C̳álculos'!G73 -> R$ 62
G49: =IF('C̳álculos'!D74="","",2) -> 2 | H49: ='C̳álculos'!D74 -> Natália Castro | K49: ='C̳álculos'!E74 -> Ultimate | M49: ='C̳álculos'!F74 -> Anual | O49: ='C̳álculos'!G74 -> R$ 62
G50: =IF('C̳álculos'!D75="","",3) -> 3 | H50: ='C̳álculos'!D75 -> Elisa Correia | K50: ='C̳álculos'!E75 -> Ultimate | M50: ='C̳álculos'!F75 -> Mensal | O50: ='C̳álculos'!G75 -> R$ 62
G51: =IF('C̳álculos'!D76="","",4) -> 4 | H51: ='C̳álculos'!D76 -> Natália Soares | K51: ='C̳álculos'!E76 -> Ultimate | M51: ='C̳álculos'!F76 -> Anual | O51: ='C̳álculos'!G76 -> R$ 62
G52: =IF('C̳álculos'!D77="","",5) -> 5 | H52: ='C̳álculos'!D77 -> Elisa Neves | K52: ='C̳álculos'!E77 -> Ultimate | M52: ='C̳álculos'!F77 -> Mensal | O52: ='C̳álculos'!G77 -> R$ 62
G53: =IF('C̳álculos'!D78="","",6) -> 6 | H53: ='C̳álculos'!D78 -> Patrícia Leite | K53: ='C̳álculos'!E78 -> Ultimate | M53: ='C̳álculos'!F78 -> Anual | O53: ='C̳álculos'!G78 -> R$ 62
G54: =IF('C̳álculos'!D79="","",7) -> 7 | H54: ='C̳álculos'!D79 -> Gabriel Santos | K54: ='C̳álculos'!E79 -> Ultimate | M54: ='C̳álculos'!F79 -> Mensal | O54: ='C̳álculos'!G79 -> R$ 62
G55: =IF('C̳álculos'!D80="","",8) -> 8 | H55: ='C̳álculos'!D80 -> Joana Silveira | K55: ='C̳álculos'!E80 -> Ultimate | M55: ='C̳álculos'!F80 -> Anual | O55: ='C̳álculos'!G80 -> R$ 62
G56: =IF('C̳álculos'!D81="","",9) -> 9 | H56: ='C̳álculos'!D81 -> André Lopes | K56: ='C̳álculos'!E81 -> Ultimate | M56: ='C̳álculos'!F81 -> Mensal | O56: ='C̳álculos'!G81 -> R$ 62
G57: =IF('C̳álculos'!D82="","",10) -> 10 | H57: ='C̳álculos'!D82 -> João Carvalho | K57: ='C̳álculos'!E82 -> Ultimate | M57: ='C̳álculos'!F82 -> Mensal | O57: ='C̳álculos'!G82 -> R$ 62
G59: Valor total = plano + add-ons − cupom. Respeita todos os filtros.
B62: Receita por plano × tipo de assinatura | J62: Oportunidades de ação
B63: Plano | D63: Mensal | E63: Trimestral | F63: Anual | G63: Total | J63: Assinantes sem renovação automática | N63: ='C̳álculos'!B58 -> 147
B64: ='C̳álculos'!A66 -> Core | D64: ='C̳álculos'!B66 -> R$ 192 | E64: ='C̳álculos'!C66 -> R$ 132 | F64: ='C̳álculos'!D66 -> R$ 120 | G64: ='C̳álculos'!E66 -> R$ 444 | J64: Receita desses assinantes | N64: ='C̳álculos'!B59 -> R$ 3,847
B65: ='C̳álculos'!A67 -> Standard | D65: ='C̳álculos'!B67 -> R$ 958 | E65: ='C̳álculos'!C67 -> R$ 395 | F65: ='C̳álculos'!D67 -> R$ 448 | G65: ='C̳álculos'!E67 -> R$ 1,801 | J65: Assinantes no plano mensal | N65: ='C̳álculos'!B60 -> 139
B66: ='C̳álculos'!A68 -> Ultimate | D66: ='C̳álculos'!B68 -> R$ 2,421 | E66: ='C̳álculos'!C68 -> R$ 1,781 | F66: ='C̳álculos'!D68 -> R$ 1,186 | G66: ='C̳álculos'!E68 -> R$ 5,388 | J66: Receita desses assinantes | N66: ='C̳álculos'!B61 -> R$ 3,571
B67: ='C̳álculos'!A69 -> Total | D67: ='C̳álculos'!B69 -> R$ 3,571 | E67: ='C̳álculos'!C69 -> R$ 2,308 | F67: ='C̳álculos'!D69 -> R$ 1,754 | G67: ='C̳álculos'!E69 -> R$ 7,633 | J67: Públicos para retenção e migração para planos mais longos.
B69: Fonte: aba Bases. Os gráficos por plano, tipo e renovação ignoram o próprio filtro para continuar mostrando a comparação. Regras e fórmulas na aba Cálculos.
